arcpy_metadata/__init__.py
arcpy_metadata/elements.py
arcpy_metadata/languages.py
arcpy_metadata/metadata_constructors.py
arcpy_metadata/metadata_editor.py
arcpy_metadata/metadata_items.py
arcpy_metadata/version.py
arcpy_metadata-1.0.0.dist-info/METADATA
arcpy_metadata-1.0.0.dist-info/WHEEL
arcpy_metadata-1.0.0.dist-info/top_level.txt
arcpy_metadata-1.0.0.dist-info/RECORD
