Metadata-Version: 2.1
Name: arcpy-metadata
Version: 1.0.0
Summary: Python metadata editing classes for ArcGIS feature classes.
Home-page: https://github.com/ucd-cws/arcpy_metadata
Author: nickrsan, thomas.maschler
Requires-Dist: python >=3.6
Requires-Dist: arcpy >=2.6
Requires-Dist: lxml >=2.0
